README.md
calculadora.py
setup.py
mi_calculadora_americana_prueba.egg-info/PKG-INFO
mi_calculadora_americana_prueba.egg-info/SOURCES.txt
mi_calculadora_americana_prueba.egg-info/dependency_links.txt
mi_calculadora_americana_prueba.egg-info/entry_points.txt
mi_calculadora_americana_prueba.egg-info/requires.txt
mi_calculadora_americana_prueba.egg-info/top_level.txt