Metadata-Version: 2.1
Name: mi-calculadora-americana-prueba
Version: 1.1.0
Summary: Una simple calculadora de Python
Home-page: https://github.com/tu_usuario/mi-calculadora
Author: Tu Nombre
Author-email: tu_correo@ejemplo.com
Classifier: Programming Language :: Python :: 3
Classifier: License :: OSI Approved :: MIT License
Classifier: Operating System :: OS Independent
Requires-Python: >=3.6
